Metadata-Version: 2.1
Name: jupyterhub-singleuser-profiles-03
Version: 0.4.1
Summary: A library allowing JupyterHub admins and users to customize and extend Jupyter workspace deployments on OpenShift
Home-page: UNKNOWN
Author: Sonal Gupta
Author-email: sonalvarshney8@gmail.com
License: GPLv3+
Platform: UNKNOWN
Requires-Dist: openshift
Requires-Dist: PyYAML
Requires-Dist: requests
Requires-Dist: jsonpath-rw
Requires-Dist: connexion[swagger-ui]
Requires-Dist: connexion
Requires-Dist: pydantic
Requires-Dist: jinja2
Requires-Dist: escapism
Requires-Dist: tornado
Requires-Dist: jupyterhub
